prioritealist/__init__.py
prioritealist/task_manager.py
prioritealist-0.2.4.dist-info/LICENSE
prioritealist-0.2.4.dist-info/METADATA
prioritealist-0.2.4.dist-info/WHEEL
prioritealist-0.2.4.dist-info/RECORD
