Metadata-Version: 2.1
Name: prioritealist
Version: 0.2.4
Summary: Priority list project for Télécom Paris Post Master Degree
Home-page: https://github.com/anatolereffet/prioritealist.git
License: MIT
Author: quentinaml
Author-email: quentin.amiel@free.fr
Requires-Python: >=3.8,<4.0
Classifier: License :: OSI Approved :: MIT License
Classifier: Programming Language :: Python :: 3
Classifier: Programming Language :: Python :: 3.8
Classifier: Programming Language :: Python :: 3.9
Classifier: Programming Language :: Python :: 3.10
Classifier: Programming Language :: Python :: 3.11
Classifier: Programming Language :: Python :: 3.12
Requires-Dist: uuid (>=1.30,<2.0)
Project-URL: Repository, https://github.com/anatolereffet/prioritealist.git
